{"tags": [], "description": "", "objects": [{"description": "", "bitmap": null, "tags": [], "classTitle": "Red goal", "points": {"exterior": [[136.0, 190.0], [135.0, 240.0], [124.0, 410.0], [138.0, 409.0], [146.0, 401.0], [157.0, 198.0], [152.0, 192.0]], "interior": []}}, {"description": "", "bitmap": null, "tags": [], "classTitle": "Red goal", "points": {"exterior": [[182.0, 159.0], [180.0, 170.0], [182.0, 180.0], [243.0, 190.0], [346.0, 203.0], [353.0, 199.0], [355.0, 186.0]], "interior": []}}, {"description": "", "bitmap": null, "tags": [], "classTitle": "Red goal", "points": {"exterior": [[362.0, 222.0], [365.0, 299.0], [372.0, 370.0], [379.0, 375.0], [389.0, 377.0], [389.0, 332.0], [382.0, 217.0], [377.0, 215.0], [366.0, 216.0]], "interior": []}}], "size": {"height": 480, "width": 640}}